MANIFEST.in
README.md
cxfreeze
cxfreeze-quickstart
setup.py
cx_Freeze/__init__.py
cx_Freeze/common.py
cx_Freeze/dist.py
cx_Freeze/finder.py
cx_Freeze/freezer.py
cx_Freeze/hooks.py
cx_Freeze/macdist.py
cx_Freeze/main.py
cx_Freeze/setupwriter.py
cx_Freeze/windist.py
cx_Freeze/initscripts/Console.py
cx_Freeze/initscripts/ConsoleSetLibPath.py
cx_Freeze/initscripts/SharedLib.py
cx_Freeze/initscripts/SharedLibSource.py
cx_Freeze/initscripts/__startup__.py
cx_Freeze/samples/PyQt4/PyQt4app.py
cx_Freeze/samples/PyQt4/setup.py
cx_Freeze/samples/PyQt5/PyQt5app.py
cx_Freeze/samples/PyQt5/setup.py
cx_Freeze/samples/Tkinter/SimpleTkApp.py
cx_Freeze/samples/Tkinter/setup.py
cx_Freeze/samples/advanced/advanced_1.py
cx_Freeze/samples/advanced/advanced_2.py
cx_Freeze/samples/advanced/setup.py
cx_Freeze/samples/advanced/modules/testfreeze_1.py
cx_Freeze/samples/advanced/modules/testfreeze_2.py
cx_Freeze/samples/asmodule/asmodule.py
cx_Freeze/samples/asmodule/setup.py
cx_Freeze/samples/matplotlib/matplotlib_eg.py
cx_Freeze/samples/matplotlib/setup.py
cx_Freeze/samples/openpyxl/setup.py
cx_Freeze/samples/openpyxl/test_openpyxl.py
cx_Freeze/samples/relimport/relimport.py
cx_Freeze/samples/relimport/setup.py
cx_Freeze/samples/relimport/pkg1/__init__.py
cx_Freeze/samples/relimport/pkg1/sub1.py
cx_Freeze/samples/relimport/pkg1/sub2.py
cx_Freeze/samples/relimport/pkg1/sub4.py
cx_Freeze/samples/relimport/pkg1/sub6.py
cx_Freeze/samples/relimport/pkg1/pkg2/__init__.py
cx_Freeze/samples/relimport/pkg1/pkg2/sub3.py
cx_Freeze/samples/relimport/pkg1/pkg2/sub5.py
cx_Freeze/samples/service/Config.py
cx_Freeze/samples/service/ServiceHandler.py
cx_Freeze/samples/service/setup.py
cx_Freeze/samples/simple/hello.py
cx_Freeze/samples/simple/setup.py
cx_Freeze/samples/wx/setup.py
cx_Freeze/samples/wx/wxapp.py
cx_Freeze/samples/zope/qotd.py
cx_Freeze/samples/zope/setup.py
cx_Freeze_395.egg-info/PKG-INFO
cx_Freeze_395.egg-info/SOURCES.txt
cx_Freeze_395.egg-info/dependency_links.txt
cx_Freeze_395.egg-info/top_level.txt
source/util.c
source/bases/Common.c
source/bases/Console.c
source/bases/Win32GUI.c
source/bases/Win32Service.c
source/bases/dummy.rc
