Metadata-Version: 1.2
Name: cx-Freeze-395
Version: 6.0b1
Summary: create standalone executables from Python scripts
Home-page: https://anthony-tuininga.github.io/cx_Freeze
Maintainer: Anthony Tuininga
Maintainer-email: anthony.tuininga@gmail.com
License: Python Software Foundation License
Keywords: freeze
Platform: UNKNOWN
Classifier: Development Status :: 5 - Production/Stable
Classifier: Intended Audience :: Developers
Classifier: License :: OSI Approved :: Python Software Foundation License
Classifier: Natural Language :: English
Classifier: Operating System :: OS Independent
Classifier: Programming Language :: C
Classifier: Programming Language :: Python
Classifier: Programming Language :: Python :: 3
Classifier: Programming Language :: Python :: 3.5
Classifier: Programming Language :: Python :: 3.6
Classifier: Programming Language :: Python :: 3 :: Only
Classifier: Topic :: Software Development :: Build Tools
Classifier: Topic :: Software Development :: Libraries :: Python Modules
Classifier: Topic :: System :: Software Distribution
Classifier: Topic :: Utilities
